<?xml version='1.0' encoding='UTF-8'?>
<GateDocument version="3">
<!-- The document's features-->

<GateDocumentFeatures>
<Feature>
  <Name className="java.lang.String">gate.SourceURL</Name>
  <Value className="java.lang.String">created from String</Value>
</Feature>
<Feature>
  <Name className="java.lang.String">nSentTo</Name>
  <Value className="java.lang.Integer">4320</Value>
</Feature>
<Feature>
  <Name className="java.lang.String">MimeType</Name>
  <Value className="java.lang.String">text/plain</Value>
</Feature>
<Feature>
  <Name className="java.lang.String">docNewLineType</Name>
  <Value className="java.lang.String"></Value>
</Feature>
<Feature>
  <Name className="java.lang.String">nSentFrom</Name>
  <Value className="java.lang.Integer">4320</Value>
</Feature>
</GateDocumentFeatures>
<!-- The document content area with serialized nodes -->

<TextWithNodes><Node id="0"/>Please<Node id="6"/> <Node id="7"/>let<Node id="10"/> <Node id="11"/>me<Node id="13"/> <Node id="14"/>know<Node id="18"/> <Node id="19"/>how<Node id="22"/> <Node id="23"/>your<Node id="27"/> <Node id="28"/>organization<Node id="40"/> <Node id="41"/>can<Node id="44"/> <Node id="45"/>help<Node id="49"/> <Node id="50"/>the<Node id="53"/> <Node id="54"/>Enron<Node id="59"/> <Node id="60"/>employees<Node id="69"/> <Node id="70"/>feel<Node id="74"/> <Node id="75"/>safer<Node id="80"/> <Node id="81"/>about<Node id="86"/> <Node id="87"/>the<Node id="90"/> <Node id="91"/>safeguard<Node id="100"/> <Node id="101"/>of<Node id="103"/> <Node id="104"/>their<Node id="109"/> <Node id="110"/>SS<Node id="112"/> <Node id="113"/>number<Node id="119"/>.<Node id="120"/></TextWithNodes>
<!-- The default annotation set -->

<AnnotationSet>
</AnnotationSet>

<!-- Named annotation set -->

<AnnotationSet Name="Original markups">
</AnnotationSet>

<!-- Named annotation set -->

<AnnotationSet Name="Key">
<Annotation Id="0" Type="Token" StartNode="0" EndNode="6">
<Feature>
  <Name className="java.lang.String">head</Name>
  <Value className="java.lang.Integer">1</Value>
</Feature>
<Feature>
  <Name className="java.lang.String">lemma</Name>
  <Value className="java.lang.String">please</Value>
</Feature>
<Feature>
  <Name className="java.lang.String">upos</Name>
  <Value className="java.lang.String">INTJ</Value>
</Feature>
<Feature>
  <Name className="java.lang.String">deprel</Name>
  <Value className="java.lang.String">discourse</Value>
</Feature>
<Feature>
  <Name className="java.lang.String">string</Name>
  <Value className="java.lang.String">Please</Value>
</Feature>
<Feature>
  <Name className="java.lang.String">category</Name>
  <Value className="java.lang.String">UH</Value>
</Feature>
</Annotation>
<Annotation Id="1" Type="Token" StartNode="7" EndNode="10">
<Feature>
  <Name className="java.lang.String">head</Name>
  <Value className="java.lang.Integer">22</Value>
</Feature>
<Feature>
  <Name className="java.lang.String">deprel</Name>
  <Value className="java.lang.String">root</Value>
</Feature>
<Feature>
  <Name className="java.lang.String">Mood</Name>
  <Value className="java.lang.String">Imp</Value>
</Feature>
<Feature>
  <Name className="java.lang.String">string</Name>
  <Value className="java.lang.String">let</Value>
</Feature>
<Feature>
  <Name className="java.lang.String">lemma</Name>
  <Value className="java.lang.String">let</Value>
</Feature>
<Feature>
  <Name className="java.lang.String">upos</Name>
  <Value className="java.lang.String">VERB</Value>
</Feature>
<Feature>
  <Name className="java.lang.String">VerbForm</Name>
  <Value className="java.lang.String">Fin</Value>
</Feature>
<Feature>
  <Name className="java.lang.String">category</Name>
  <Value className="java.lang.String">VB</Value>
</Feature>
</Annotation>
<Annotation Id="2" Type="Token" StartNode="11" EndNode="13">
<Feature>
  <Name className="java.lang.String">head</Name>
  <Value className="java.lang.Integer">1</Value>
</Feature>
<Feature>
  <Name className="java.lang.String">deprel</Name>
  <Value className="java.lang.String">obj</Value>
</Feature>
<Feature>
  <Name className="java.lang.String">string</Name>
  <Value className="java.lang.String">me</Value>
</Feature>
<Feature>
  <Name className="java.lang.String">Number</Name>
  <Value className="java.lang.String">Sing</Value>
</Feature>
<Feature>
  <Name className="java.lang.String">lemma</Name>
  <Value className="java.lang.String">I</Value>
</Feature>
<Feature>
  <Name className="java.lang.String">upos</Name>
  <Value className="java.lang.String">PRON</Value>
</Feature>
<Feature>
  <Name className="java.lang.String">category</Name>
  <Value className="java.lang.String">PRP</Value>
</Feature>
<Feature>
  <Name className="java.lang.String">Person</Name>
  <Value className="java.lang.String">1</Value>
</Feature>
<Feature>
  <Name className="java.lang.String">Case</Name>
  <Value className="java.lang.String">Acc</Value>
</Feature>
<Feature>
  <Name className="java.lang.String">PronType</Name>
  <Value className="java.lang.String">Prs</Value>
</Feature>
</Annotation>
<Annotation Id="3" Type="Token" StartNode="14" EndNode="18">
<Feature>
  <Name className="java.lang.String">head</Name>
  <Value className="java.lang.Integer">1</Value>
</Feature>
<Feature>
  <Name className="java.lang.String">deprel</Name>
  <Value className="java.lang.String">xcomp</Value>
</Feature>
<Feature>
  <Name className="java.lang.String">string</Name>
  <Value className="java.lang.String">know</Value>
</Feature>
<Feature>
  <Name className="java.lang.String">lemma</Name>
  <Value className="java.lang.String">know</Value>
</Feature>
<Feature>
  <Name className="java.lang.String">upos</Name>
  <Value className="java.lang.String">VERB</Value>
</Feature>
<Feature>
  <Name className="java.lang.String">VerbForm</Name>
  <Value className="java.lang.String">Inf</Value>
</Feature>
<Feature>
  <Name className="java.lang.String">category</Name>
  <Value className="java.lang.String">VB</Value>
</Feature>
</Annotation>
<Annotation Id="4" Type="Token" StartNode="19" EndNode="22">
<Feature>
  <Name className="java.lang.String">head</Name>
  <Value className="java.lang.Integer">8</Value>
</Feature>
<Feature>
  <Name className="java.lang.String">deprel</Name>
  <Value className="java.lang.String">advmod</Value>
</Feature>
<Feature>
  <Name className="java.lang.String">string</Name>
  <Value className="java.lang.String">how</Value>
</Feature>
<Feature>
  <Name className="java.lang.String">lemma</Name>
  <Value className="java.lang.String">how</Value>
</Feature>
<Feature>
  <Name className="java.lang.String">upos</Name>
  <Value className="java.lang.String">ADV</Value>
</Feature>
<Feature>
  <Name className="java.lang.String">category</Name>
  <Value className="java.lang.String">WRB</Value>
</Feature>
<Feature>
  <Name className="java.lang.String">PronType</Name>
  <Value className="java.lang.String">Int</Value>
</Feature>
</Annotation>
<Annotation Id="5" Type="Token" StartNode="23" EndNode="27">
<Feature>
  <Name className="java.lang.String">head</Name>
  <Value className="java.lang.Integer">6</Value>
</Feature>
<Feature>
  <Name className="java.lang.String">deprel</Name>
  <Value className="java.lang.String">nmod:poss</Value>
</Feature>
<Feature>
  <Name className="java.lang.String">string</Name>
  <Value className="java.lang.String">your</Value>
</Feature>
<Feature>
  <Name className="java.lang.String">lemma</Name>
  <Value className="java.lang.String">you</Value>
</Feature>
<Feature>
  <Name className="java.lang.String">upos</Name>
  <Value className="java.lang.String">PRON</Value>
</Feature>
<Feature>
  <Name className="java.lang.String">Poss</Name>
  <Value className="java.lang.String">Yes</Value>
</Feature>
<Feature>
  <Name className="java.lang.String">category</Name>
  <Value className="java.lang.String">PRP$</Value>
</Feature>
<Feature>
  <Name className="java.lang.String">Person</Name>
  <Value className="java.lang.String">2</Value>
</Feature>
<Feature>
  <Name className="java.lang.String">PronType</Name>
  <Value className="java.lang.String">Prs</Value>
</Feature>
</Annotation>
<Annotation Id="6" Type="Token" StartNode="28" EndNode="40">
<Feature>
  <Name className="java.lang.String">head</Name>
  <Value className="java.lang.Integer">8</Value>
</Feature>
<Feature>
  <Name className="java.lang.String">deprel</Name>
  <Value className="java.lang.String">nsubj</Value>
</Feature>
<Feature>
  <Name className="java.lang.String">string</Name>
  <Value className="java.lang.String">organization</Value>
</Feature>
<Feature>
  <Name className="java.lang.String">Number</Name>
  <Value className="java.lang.String">Sing</Value>
</Feature>
<Feature>
  <Name className="java.lang.String">lemma</Name>
  <Value className="java.lang.String">organization</Value>
</Feature>
<Feature>
  <Name className="java.lang.String">upos</Name>
  <Value className="java.lang.String">NOUN</Value>
</Feature>
<Feature>
  <Name className="java.lang.String">category</Name>
  <Value className="java.lang.String">NN</Value>
</Feature>
</Annotation>
<Annotation Id="7" Type="Token" StartNode="41" EndNode="44">
<Feature>
  <Name className="java.lang.String">head</Name>
  <Value className="java.lang.Integer">8</Value>
</Feature>
<Feature>
  <Name className="java.lang.String">deprel</Name>
  <Value className="java.lang.String">aux</Value>
</Feature>
<Feature>
  <Name className="java.lang.String">string</Name>
  <Value className="java.lang.String">can</Value>
</Feature>
<Feature>
  <Name className="java.lang.String">lemma</Name>
  <Value className="java.lang.String">can</Value>
</Feature>
<Feature>
  <Name className="java.lang.String">upos</Name>
  <Value className="java.lang.String">AUX</Value>
</Feature>
<Feature>
  <Name className="java.lang.String">VerbForm</Name>
  <Value className="java.lang.String">Fin</Value>
</Feature>
<Feature>
  <Name className="java.lang.String">category</Name>
  <Value className="java.lang.String">MD</Value>
</Feature>
</Annotation>
<Annotation Id="8" Type="Token" StartNode="45" EndNode="49">
<Feature>
  <Name className="java.lang.String">head</Name>
  <Value className="java.lang.Integer">3</Value>
</Feature>
<Feature>
  <Name className="java.lang.String">deprel</Name>
  <Value className="java.lang.String">ccomp</Value>
</Feature>
<Feature>
  <Name className="java.lang.String">string</Name>
  <Value className="java.lang.String">help</Value>
</Feature>
<Feature>
  <Name className="java.lang.String">lemma</Name>
  <Value className="java.lang.String">help</Value>
</Feature>
<Feature>
  <Name className="java.lang.String">upos</Name>
  <Value className="java.lang.String">VERB</Value>
</Feature>
<Feature>
  <Name className="java.lang.String">VerbForm</Name>
  <Value className="java.lang.String">Inf</Value>
</Feature>
<Feature>
  <Name className="java.lang.String">category</Name>
  <Value className="java.lang.String">VB</Value>
</Feature>
</Annotation>
<Annotation Id="9" Type="Token" StartNode="50" EndNode="53">
<Feature>
  <Name className="java.lang.String">head</Name>
  <Value className="java.lang.Integer">11</Value>
</Feature>
<Feature>
  <Name className="java.lang.String">deprel</Name>
  <Value className="java.lang.String">det</Value>
</Feature>
<Feature>
  <Name className="java.lang.String">string</Name>
  <Value className="java.lang.String">the</Value>
</Feature>
<Feature>
  <Name className="java.lang.String">lemma</Name>
  <Value className="java.lang.String">the</Value>
</Feature>
<Feature>
  <Name className="java.lang.String">upos</Name>
  <Value className="java.lang.String">DET</Value>
</Feature>
<Feature>
  <Name className="java.lang.String">category</Name>
  <Value className="java.lang.String">DT</Value>
</Feature>
<Feature>
  <Name className="java.lang.String">Definite</Name>
  <Value className="java.lang.String">Def</Value>
</Feature>
<Feature>
  <Name className="java.lang.String">PronType</Name>
  <Value className="java.lang.String">Art</Value>
</Feature>
</Annotation>
<Annotation Id="10" Type="Token" StartNode="54" EndNode="59">
<Feature>
  <Name className="java.lang.String">head</Name>
  <Value className="java.lang.Integer">11</Value>
</Feature>
<Feature>
  <Name className="java.lang.String">deprel</Name>
  <Value className="java.lang.String">compound</Value>
</Feature>
<Feature>
  <Name className="java.lang.String">string</Name>
  <Value className="java.lang.String">Enron</Value>
</Feature>
<Feature>
  <Name className="java.lang.String">Number</Name>
  <Value className="java.lang.String">Sing</Value>
</Feature>
<Feature>
  <Name className="java.lang.String">lemma</Name>
  <Value className="java.lang.String">Enron</Value>
</Feature>
<Feature>
  <Name className="java.lang.String">upos</Name>
  <Value className="java.lang.String">PROPN</Value>
</Feature>
<Feature>
  <Name className="java.lang.String">category</Name>
  <Value className="java.lang.String">NNP</Value>
</Feature>
</Annotation>
<Annotation Id="11" Type="Token" StartNode="60" EndNode="69">
<Feature>
  <Name className="java.lang.String">head</Name>
  <Value className="java.lang.Integer">12</Value>
</Feature>
<Feature>
  <Name className="java.lang.String">deprel</Name>
  <Value className="java.lang.String">nsubj</Value>
</Feature>
<Feature>
  <Name className="java.lang.String">string</Name>
  <Value className="java.lang.String">employees</Value>
</Feature>
<Feature>
  <Name className="java.lang.String">Number</Name>
  <Value className="java.lang.String">Plur</Value>
</Feature>
<Feature>
  <Name className="java.lang.String">lemma</Name>
  <Value className="java.lang.String">employee</Value>
</Feature>
<Feature>
  <Name className="java.lang.String">upos</Name>
  <Value className="java.lang.String">NOUN</Value>
</Feature>
<Feature>
  <Name className="java.lang.String">category</Name>
  <Value className="java.lang.String">NNS</Value>
</Feature>
</Annotation>
<Annotation Id="12" Type="Token" StartNode="70" EndNode="74">
<Feature>
  <Name className="java.lang.String">head</Name>
  <Value className="java.lang.Integer">8</Value>
</Feature>
<Feature>
  <Name className="java.lang.String">deprel</Name>
  <Value className="java.lang.String">ccomp</Value>
</Feature>
<Feature>
  <Name className="java.lang.String">string</Name>
  <Value className="java.lang.String">feel</Value>
</Feature>
<Feature>
  <Name className="java.lang.String">lemma</Name>
  <Value className="java.lang.String">feel</Value>
</Feature>
<Feature>
  <Name className="java.lang.String">upos</Name>
  <Value className="java.lang.String">VERB</Value>
</Feature>
<Feature>
  <Name className="java.lang.String">VerbForm</Name>
  <Value className="java.lang.String">Inf</Value>
</Feature>
<Feature>
  <Name className="java.lang.String">category</Name>
  <Value className="java.lang.String">VB</Value>
</Feature>
</Annotation>
<Annotation Id="13" Type="Token" StartNode="75" EndNode="80">
<Feature>
  <Name className="java.lang.String">head</Name>
  <Value className="java.lang.Integer">12</Value>
</Feature>
<Feature>
  <Name className="java.lang.String">deprel</Name>
  <Value className="java.lang.String">xcomp</Value>
</Feature>
<Feature>
  <Name className="java.lang.String">string</Name>
  <Value className="java.lang.String">safer</Value>
</Feature>
<Feature>
  <Name className="java.lang.String">Degree</Name>
  <Value className="java.lang.String">Cmp</Value>
</Feature>
<Feature>
  <Name className="java.lang.String">lemma</Name>
  <Value className="java.lang.String">safer</Value>
</Feature>
<Feature>
  <Name className="java.lang.String">upos</Name>
  <Value className="java.lang.String">ADJ</Value>
</Feature>
<Feature>
  <Name className="java.lang.String">category</Name>
  <Value className="java.lang.String">JJR</Value>
</Feature>
</Annotation>
<Annotation Id="14" Type="Token" StartNode="81" EndNode="86">
<Feature>
  <Name className="java.lang.String">head</Name>
  <Value className="java.lang.Integer">16</Value>
</Feature>
<Feature>
  <Name className="java.lang.String">lemma</Name>
  <Value className="java.lang.String">about</Value>
</Feature>
<Feature>
  <Name className="java.lang.String">upos</Name>
  <Value className="java.lang.String">ADP</Value>
</Feature>
<Feature>
  <Name className="java.lang.String">deprel</Name>
  <Value className="java.lang.String">case</Value>
</Feature>
<Feature>
  <Name className="java.lang.String">string</Name>
  <Value className="java.lang.String">about</Value>
</Feature>
<Feature>
  <Name className="java.lang.String">category</Name>
  <Value className="java.lang.String">IN</Value>
</Feature>
</Annotation>
<Annotation Id="15" Type="Token" StartNode="87" EndNode="90">
<Feature>
  <Name className="java.lang.String">head</Name>
  <Value className="java.lang.Integer">16</Value>
</Feature>
<Feature>
  <Name className="java.lang.String">deprel</Name>
  <Value className="java.lang.String">det</Value>
</Feature>
<Feature>
  <Name className="java.lang.String">string</Name>
  <Value className="java.lang.String">the</Value>
</Feature>
<Feature>
  <Name className="java.lang.String">lemma</Name>
  <Value className="java.lang.String">the</Value>
</Feature>
<Feature>
  <Name className="java.lang.String">upos</Name>
  <Value className="java.lang.String">DET</Value>
</Feature>
<Feature>
  <Name className="java.lang.String">category</Name>
  <Value className="java.lang.String">DT</Value>
</Feature>
<Feature>
  <Name className="java.lang.String">Definite</Name>
  <Value className="java.lang.String">Def</Value>
</Feature>
<Feature>
  <Name className="java.lang.String">PronType</Name>
  <Value className="java.lang.String">Art</Value>
</Feature>
</Annotation>
<Annotation Id="16" Type="Token" StartNode="91" EndNode="100">
<Feature>
  <Name className="java.lang.String">head</Name>
  <Value className="java.lang.Integer">13</Value>
</Feature>
<Feature>
  <Name className="java.lang.String">deprel</Name>
  <Value className="java.lang.String">obl</Value>
</Feature>
<Feature>
  <Name className="java.lang.String">string</Name>
  <Value className="java.lang.String">safeguard</Value>
</Feature>
<Feature>
  <Name className="java.lang.String">Number</Name>
  <Value className="java.lang.String">Sing</Value>
</Feature>
<Feature>
  <Name className="java.lang.String">lemma</Name>
  <Value className="java.lang.String">safeguard</Value>
</Feature>
<Feature>
  <Name className="java.lang.String">upos</Name>
  <Value className="java.lang.String">NOUN</Value>
</Feature>
<Feature>
  <Name className="java.lang.String">category</Name>
  <Value className="java.lang.String">NN</Value>
</Feature>
</Annotation>
<Annotation Id="17" Type="Token" StartNode="101" EndNode="103">
<Feature>
  <Name className="java.lang.String">head</Name>
  <Value className="java.lang.Integer">20</Value>
</Feature>
<Feature>
  <Name className="java.lang.String">lemma</Name>
  <Value className="java.lang.String">of</Value>
</Feature>
<Feature>
  <Name className="java.lang.String">upos</Name>
  <Value className="java.lang.String">ADP</Value>
</Feature>
<Feature>
  <Name className="java.lang.String">deprel</Name>
  <Value className="java.lang.String">case</Value>
</Feature>
<Feature>
  <Name className="java.lang.String">string</Name>
  <Value className="java.lang.String">of</Value>
</Feature>
<Feature>
  <Name className="java.lang.String">category</Name>
  <Value className="java.lang.String">IN</Value>
</Feature>
</Annotation>
<Annotation Id="18" Type="Token" StartNode="104" EndNode="109">
<Feature>
  <Name className="java.lang.String">head</Name>
  <Value className="java.lang.Integer">20</Value>
</Feature>
<Feature>
  <Name className="java.lang.String">deprel</Name>
  <Value className="java.lang.String">nmod:poss</Value>
</Feature>
<Feature>
  <Name className="java.lang.String">string</Name>
  <Value className="java.lang.String">their</Value>
</Feature>
<Feature>
  <Name className="java.lang.String">Number</Name>
  <Value className="java.lang.String">Plur</Value>
</Feature>
<Feature>
  <Name className="java.lang.String">lemma</Name>
  <Value className="java.lang.String">they</Value>
</Feature>
<Feature>
  <Name className="java.lang.String">upos</Name>
  <Value className="java.lang.String">PRON</Value>
</Feature>
<Feature>
  <Name className="java.lang.String">Poss</Name>
  <Value className="java.lang.String">Yes</Value>
</Feature>
<Feature>
  <Name className="java.lang.String">category</Name>
  <Value className="java.lang.String">PRP$</Value>
</Feature>
<Feature>
  <Name className="java.lang.String">Person</Name>
  <Value className="java.lang.String">3</Value>
</Feature>
<Feature>
  <Name className="java.lang.String">PronType</Name>
  <Value className="java.lang.String">Prs</Value>
</Feature>
</Annotation>
<Annotation Id="19" Type="Token" StartNode="110" EndNode="112">
<Feature>
  <Name className="java.lang.String">head</Name>
  <Value className="java.lang.Integer">20</Value>
</Feature>
<Feature>
  <Name className="java.lang.String">deprel</Name>
  <Value className="java.lang.String">compound</Value>
</Feature>
<Feature>
  <Name className="java.lang.String">string</Name>
  <Value className="java.lang.String">SS</Value>
</Feature>
<Feature>
  <Name className="java.lang.String">Number</Name>
  <Value className="java.lang.String">Sing</Value>
</Feature>
<Feature>
  <Name className="java.lang.String">lemma</Name>
  <Value className="java.lang.String">ss</Value>
</Feature>
<Feature>
  <Name className="java.lang.String">upos</Name>
  <Value className="java.lang.String">NOUN</Value>
</Feature>
<Feature>
  <Name className="java.lang.String">category</Name>
  <Value className="java.lang.String">NN</Value>
</Feature>
</Annotation>
<Annotation Id="20" Type="Token" StartNode="113" EndNode="119">
<Feature>
  <Name className="java.lang.String">head</Name>
  <Value className="java.lang.Integer">16</Value>
</Feature>
<Feature>
  <Name className="java.lang.String">deprel</Name>
  <Value className="java.lang.String">nmod</Value>
</Feature>
<Feature>
  <Name className="java.lang.String">string</Name>
  <Value className="java.lang.String">number</Value>
</Feature>
<Feature>
  <Name className="java.lang.String">Number</Name>
  <Value className="java.lang.String">Sing</Value>
</Feature>
<Feature>
  <Name className="java.lang.String">lemma</Name>
  <Value className="java.lang.String">number</Value>
</Feature>
<Feature>
  <Name className="java.lang.String">upos</Name>
  <Value className="java.lang.String">NOUN</Value>
</Feature>
<Feature>
  <Name className="java.lang.String">category</Name>
  <Value className="java.lang.String">NN</Value>
</Feature>
</Annotation>
<Annotation Id="21" Type="Token" StartNode="119" EndNode="120">
<Feature>
  <Name className="java.lang.String">head</Name>
  <Value className="java.lang.Integer">1</Value>
</Feature>
<Feature>
  <Name className="java.lang.String">lemma</Name>
  <Value className="java.lang.String">.</Value>
</Feature>
<Feature>
  <Name className="java.lang.String">upos</Name>
  <Value className="java.lang.String">PUNCT</Value>
</Feature>
<Feature>
  <Name className="java.lang.String">deprel</Name>
  <Value className="java.lang.String">punct</Value>
</Feature>
<Feature>
  <Name className="java.lang.String">string</Name>
  <Value className="java.lang.String">.</Value>
</Feature>
<Feature>
  <Name className="java.lang.String">category</Name>
  <Value className="java.lang.String">.</Value>
</Feature>
</Annotation>
<Annotation Id="22" Type="Sentence" StartNode="0" EndNode="120">
<Feature>
  <Name className="java.lang.String">gate.conversion.nLineTo</Name>
  <Value className="java.lang.Integer">81350</Value>
</Feature>
<Feature>
  <Name className="java.lang.String">gate.conversion.nLineFrom</Name>
  <Value className="java.lang.Integer">81328</Value>
</Feature>
<Feature>
  <Name className="java.lang.String">gate.conversion.sentComments</Name>
  <Value className="gate.corpora.ObjectWrapper"><![CDATA[<?xml version='1.1'?><gate.corpora.ObjectWrapper><value class="list"><string># sent_id = email-enronsent03_01-0073</string><string># text = Please let me know how your organization can help the Enron employees feel safer about the safeguard of their SS number.</string></value></gate.corpora.ObjectWrapper>]]></Value>
</Feature>
<Feature>
  <Name className="java.lang.String">gate.conversion.nSent</Name>
  <Value className="java.lang.Integer">4320</Value>
</Feature>
<Feature>
  <Name className="java.lang.String">gate.conversion.sentId</Name>
  <Value className="java.lang.String"></Value>
</Feature>
</Annotation>
</AnnotationSet>

</GateDocument>
