<?xml version='1.0' encoding='UTF-8'?>
<GateDocument version="3">
<!-- The document's features-->

<GateDocumentFeatures>
<Feature>
  <Name className="java.lang.String">gate.SourceURL</Name>
  <Value className="java.lang.String">created from String</Value>
</Feature>
<Feature>
  <Name className="java.lang.String">nSentTo</Name>
  <Value className="java.lang.Integer">2301</Value>
</Feature>
<Feature>
  <Name className="java.lang.String">MimeType</Name>
  <Value className="java.lang.String">text/plain</Value>
</Feature>
<Feature>
  <Name className="java.lang.String">docNewLineType</Name>
  <Value className="java.lang.String"></Value>
</Feature>
<Feature>
  <Name className="java.lang.String">nSentFrom</Name>
  <Value className="java.lang.Integer">2301</Value>
</Feature>
</GateDocumentFeatures>
<!-- The document content area with serialized nodes -->

<TextWithNodes><Node id="0"/>This<Node id="4"/> <Node id="5"/>email<Node id="10"/> <Node id="11"/>and<Node id="14"/> <Node id="15"/>any<Node id="18"/> <Node id="19"/>files<Node id="24"/> <Node id="25"/>transmitted<Node id="36"/> <Node id="37"/>with<Node id="41"/> <Node id="42"/>it<Node id="44"/> <Node id="45"/>from<Node id="49"/> <Node id="50"/>the<Node id="53"/> <Node id="54"/>ElPaso<Node id="60"/> <Node id="61"/>Corporation<Node id="72"/> <Node id="73"/>are<Node id="76"/> <Node id="77"/>confidential<Node id="89"/> <Node id="90"/>and<Node id="93"/> <Node id="94"/>intended<Node id="102"/> <Node id="103"/>solely<Node id="109"/> <Node id="110"/>for<Node id="113"/> <Node id="114"/>the<Node id="117"/> <Node id="118"/>use<Node id="121"/> <Node id="122"/>of<Node id="124"/> <Node id="125"/>the<Node id="128"/> <Node id="129"/>individual<Node id="139"/> <Node id="140"/>or<Node id="142"/> <Node id="143"/>entity<Node id="149"/> <Node id="150"/>to<Node id="152"/> <Node id="153"/>whom<Node id="157"/> <Node id="158"/>they<Node id="162"/> <Node id="163"/>are<Node id="166"/> <Node id="167"/>addressed<Node id="176"/>.<Node id="177"/></TextWithNodes>
<!-- The default annotation set -->

<AnnotationSet>
</AnnotationSet>

<!-- Named annotation set -->

<AnnotationSet Name="Original markups">
</AnnotationSet>

<!-- Named annotation set -->

<AnnotationSet Name="Key">
<Annotation Id="0" Type="Token" StartNode="0" EndNode="4">
<Feature>
  <Name className="java.lang.String">head</Name>
  <Value className="java.lang.Integer">1</Value>
</Feature>
<Feature>
  <Name className="java.lang.String">deprel</Name>
  <Value className="java.lang.String">det</Value>
</Feature>
<Feature>
  <Name className="java.lang.String">string</Name>
  <Value className="java.lang.String">This</Value>
</Feature>
<Feature>
  <Name className="java.lang.String">Number</Name>
  <Value className="java.lang.String">Sing</Value>
</Feature>
<Feature>
  <Name className="java.lang.String">lemma</Name>
  <Value className="java.lang.String">this</Value>
</Feature>
<Feature>
  <Name className="java.lang.String">upos</Name>
  <Value className="java.lang.String">DET</Value>
</Feature>
<Feature>
  <Name className="java.lang.String">category</Name>
  <Value className="java.lang.String">DT</Value>
</Feature>
<Feature>
  <Name className="java.lang.String">PronType</Name>
  <Value className="java.lang.String">Dem</Value>
</Feature>
</Annotation>
<Annotation Id="1" Type="Token" StartNode="5" EndNode="10">
<Feature>
  <Name className="java.lang.String">head</Name>
  <Value className="java.lang.Integer">13</Value>
</Feature>
<Feature>
  <Name className="java.lang.String">deprel</Name>
  <Value className="java.lang.String">nsubj:pass</Value>
</Feature>
<Feature>
  <Name className="java.lang.String">string</Name>
  <Value className="java.lang.String">email</Value>
</Feature>
<Feature>
  <Name className="java.lang.String">Number</Name>
  <Value className="java.lang.String">Sing</Value>
</Feature>
<Feature>
  <Name className="java.lang.String">lemma</Name>
  <Value className="java.lang.String">email</Value>
</Feature>
<Feature>
  <Name className="java.lang.String">upos</Name>
  <Value className="java.lang.String">NOUN</Value>
</Feature>
<Feature>
  <Name className="java.lang.String">category</Name>
  <Value className="java.lang.String">NN</Value>
</Feature>
</Annotation>
<Annotation Id="2" Type="Token" StartNode="11" EndNode="14">
<Feature>
  <Name className="java.lang.String">head</Name>
  <Value className="java.lang.Integer">4</Value>
</Feature>
<Feature>
  <Name className="java.lang.String">lemma</Name>
  <Value className="java.lang.String">and</Value>
</Feature>
<Feature>
  <Name className="java.lang.String">upos</Name>
  <Value className="java.lang.String">CCONJ</Value>
</Feature>
<Feature>
  <Name className="java.lang.String">deprel</Name>
  <Value className="java.lang.String">cc</Value>
</Feature>
<Feature>
  <Name className="java.lang.String">string</Name>
  <Value className="java.lang.String">and</Value>
</Feature>
<Feature>
  <Name className="java.lang.String">category</Name>
  <Value className="java.lang.String">CC</Value>
</Feature>
</Annotation>
<Annotation Id="3" Type="Token" StartNode="15" EndNode="18">
<Feature>
  <Name className="java.lang.String">head</Name>
  <Value className="java.lang.Integer">4</Value>
</Feature>
<Feature>
  <Name className="java.lang.String">lemma</Name>
  <Value className="java.lang.String">any</Value>
</Feature>
<Feature>
  <Name className="java.lang.String">upos</Name>
  <Value className="java.lang.String">DET</Value>
</Feature>
<Feature>
  <Name className="java.lang.String">deprel</Name>
  <Value className="java.lang.String">det</Value>
</Feature>
<Feature>
  <Name className="java.lang.String">string</Name>
  <Value className="java.lang.String">any</Value>
</Feature>
<Feature>
  <Name className="java.lang.String">category</Name>
  <Value className="java.lang.String">DT</Value>
</Feature>
</Annotation>
<Annotation Id="4" Type="Token" StartNode="19" EndNode="24">
<Feature>
  <Name className="java.lang.String">head</Name>
  <Value className="java.lang.Integer">1</Value>
</Feature>
<Feature>
  <Name className="java.lang.String">deprel</Name>
  <Value className="java.lang.String">conj</Value>
</Feature>
<Feature>
  <Name className="java.lang.String">string</Name>
  <Value className="java.lang.String">files</Value>
</Feature>
<Feature>
  <Name className="java.lang.String">Number</Name>
  <Value className="java.lang.String">Plur</Value>
</Feature>
<Feature>
  <Name className="java.lang.String">lemma</Name>
  <Value className="java.lang.String">file</Value>
</Feature>
<Feature>
  <Name className="java.lang.String">upos</Name>
  <Value className="java.lang.String">NOUN</Value>
</Feature>
<Feature>
  <Name className="java.lang.String">category</Name>
  <Value className="java.lang.String">NNS</Value>
</Feature>
</Annotation>
<Annotation Id="5" Type="Token" StartNode="25" EndNode="36">
<Feature>
  <Name className="java.lang.String">Tense</Name>
  <Value className="java.lang.String">Past</Value>
</Feature>
<Feature>
  <Name className="java.lang.String">head</Name>
  <Value className="java.lang.Integer">4</Value>
</Feature>
<Feature>
  <Name className="java.lang.String">deprel</Name>
  <Value className="java.lang.String">acl</Value>
</Feature>
<Feature>
  <Name className="java.lang.String">string</Name>
  <Value className="java.lang.String">transmitted</Value>
</Feature>
<Feature>
  <Name className="java.lang.String">lemma</Name>
  <Value className="java.lang.String">transmit</Value>
</Feature>
<Feature>
  <Name className="java.lang.String">upos</Name>
  <Value className="java.lang.String">VERB</Value>
</Feature>
<Feature>
  <Name className="java.lang.String">VerbForm</Name>
  <Value className="java.lang.String">Part</Value>
</Feature>
<Feature>
  <Name className="java.lang.String">category</Name>
  <Value className="java.lang.String">VBN</Value>
</Feature>
</Annotation>
<Annotation Id="6" Type="Token" StartNode="37" EndNode="41">
<Feature>
  <Name className="java.lang.String">head</Name>
  <Value className="java.lang.Integer">7</Value>
</Feature>
<Feature>
  <Name className="java.lang.String">lemma</Name>
  <Value className="java.lang.String">with</Value>
</Feature>
<Feature>
  <Name className="java.lang.String">upos</Name>
  <Value className="java.lang.String">ADP</Value>
</Feature>
<Feature>
  <Name className="java.lang.String">deprel</Name>
  <Value className="java.lang.String">case</Value>
</Feature>
<Feature>
  <Name className="java.lang.String">string</Name>
  <Value className="java.lang.String">with</Value>
</Feature>
<Feature>
  <Name className="java.lang.String">category</Name>
  <Value className="java.lang.String">IN</Value>
</Feature>
</Annotation>
<Annotation Id="7" Type="Token" StartNode="42" EndNode="44">
<Feature>
  <Name className="java.lang.String">head</Name>
  <Value className="java.lang.Integer">5</Value>
</Feature>
<Feature>
  <Name className="java.lang.String">deprel</Name>
  <Value className="java.lang.String">obl</Value>
</Feature>
<Feature>
  <Name className="java.lang.String">string</Name>
  <Value className="java.lang.String">it</Value>
</Feature>
<Feature>
  <Name className="java.lang.String">Number</Name>
  <Value className="java.lang.String">Sing</Value>
</Feature>
<Feature>
  <Name className="java.lang.String">lemma</Name>
  <Value className="java.lang.String">it</Value>
</Feature>
<Feature>
  <Name className="java.lang.String">upos</Name>
  <Value className="java.lang.String">PRON</Value>
</Feature>
<Feature>
  <Name className="java.lang.String">Gender</Name>
  <Value className="java.lang.String">Neut</Value>
</Feature>
<Feature>
  <Name className="java.lang.String">category</Name>
  <Value className="java.lang.String">PRP</Value>
</Feature>
<Feature>
  <Name className="java.lang.String">Person</Name>
  <Value className="java.lang.String">3</Value>
</Feature>
<Feature>
  <Name className="java.lang.String">Case</Name>
  <Value className="java.lang.String">Acc</Value>
</Feature>
<Feature>
  <Name className="java.lang.String">PronType</Name>
  <Value className="java.lang.String">Prs</Value>
</Feature>
</Annotation>
<Annotation Id="8" Type="Token" StartNode="45" EndNode="49">
<Feature>
  <Name className="java.lang.String">head</Name>
  <Value className="java.lang.Integer">11</Value>
</Feature>
<Feature>
  <Name className="java.lang.String">lemma</Name>
  <Value className="java.lang.String">from</Value>
</Feature>
<Feature>
  <Name className="java.lang.String">upos</Name>
  <Value className="java.lang.String">ADP</Value>
</Feature>
<Feature>
  <Name className="java.lang.String">deprel</Name>
  <Value className="java.lang.String">case</Value>
</Feature>
<Feature>
  <Name className="java.lang.String">string</Name>
  <Value className="java.lang.String">from</Value>
</Feature>
<Feature>
  <Name className="java.lang.String">category</Name>
  <Value className="java.lang.String">IN</Value>
</Feature>
</Annotation>
<Annotation Id="9" Type="Token" StartNode="50" EndNode="53">
<Feature>
  <Name className="java.lang.String">head</Name>
  <Value className="java.lang.Integer">11</Value>
</Feature>
<Feature>
  <Name className="java.lang.String">deprel</Name>
  <Value className="java.lang.String">det</Value>
</Feature>
<Feature>
  <Name className="java.lang.String">string</Name>
  <Value className="java.lang.String">the</Value>
</Feature>
<Feature>
  <Name className="java.lang.String">lemma</Name>
  <Value className="java.lang.String">the</Value>
</Feature>
<Feature>
  <Name className="java.lang.String">upos</Name>
  <Value className="java.lang.String">DET</Value>
</Feature>
<Feature>
  <Name className="java.lang.String">category</Name>
  <Value className="java.lang.String">DT</Value>
</Feature>
<Feature>
  <Name className="java.lang.String">Definite</Name>
  <Value className="java.lang.String">Def</Value>
</Feature>
<Feature>
  <Name className="java.lang.String">PronType</Name>
  <Value className="java.lang.String">Art</Value>
</Feature>
</Annotation>
<Annotation Id="10" Type="Token" StartNode="54" EndNode="60">
<Feature>
  <Name className="java.lang.String">head</Name>
  <Value className="java.lang.Integer">11</Value>
</Feature>
<Feature>
  <Name className="java.lang.String">deprel</Name>
  <Value className="java.lang.String">compound</Value>
</Feature>
<Feature>
  <Name className="java.lang.String">string</Name>
  <Value className="java.lang.String">ElPaso</Value>
</Feature>
<Feature>
  <Name className="java.lang.String">Number</Name>
  <Value className="java.lang.String">Sing</Value>
</Feature>
<Feature>
  <Name className="java.lang.String">lemma</Name>
  <Value className="java.lang.String">ElPaso</Value>
</Feature>
<Feature>
  <Name className="java.lang.String">upos</Name>
  <Value className="java.lang.String">PROPN</Value>
</Feature>
<Feature>
  <Name className="java.lang.String">category</Name>
  <Value className="java.lang.String">NNP</Value>
</Feature>
</Annotation>
<Annotation Id="11" Type="Token" StartNode="61" EndNode="72">
<Feature>
  <Name className="java.lang.String">head</Name>
  <Value className="java.lang.Integer">5</Value>
</Feature>
<Feature>
  <Name className="java.lang.String">deprel</Name>
  <Value className="java.lang.String">obl</Value>
</Feature>
<Feature>
  <Name className="java.lang.String">string</Name>
  <Value className="java.lang.String">Corporation</Value>
</Feature>
<Feature>
  <Name className="java.lang.String">Number</Name>
  <Value className="java.lang.String">Sing</Value>
</Feature>
<Feature>
  <Name className="java.lang.String">lemma</Name>
  <Value className="java.lang.String">Corporation</Value>
</Feature>
<Feature>
  <Name className="java.lang.String">upos</Name>
  <Value className="java.lang.String">PROPN</Value>
</Feature>
<Feature>
  <Name className="java.lang.String">category</Name>
  <Value className="java.lang.String">NNP</Value>
</Feature>
</Annotation>
<Annotation Id="12" Type="Token" StartNode="73" EndNode="76">
<Feature>
  <Name className="java.lang.String">Tense</Name>
  <Value className="java.lang.String">Pres</Value>
</Feature>
<Feature>
  <Name className="java.lang.String">head</Name>
  <Value className="java.lang.Integer">13</Value>
</Feature>
<Feature>
  <Name className="java.lang.String">deprel</Name>
  <Value className="java.lang.String">aux:pass</Value>
</Feature>
<Feature>
  <Name className="java.lang.String">Mood</Name>
  <Value className="java.lang.String">Ind</Value>
</Feature>
<Feature>
  <Name className="java.lang.String">string</Name>
  <Value className="java.lang.String">are</Value>
</Feature>
<Feature>
  <Name className="java.lang.String">lemma</Name>
  <Value className="java.lang.String">be</Value>
</Feature>
<Feature>
  <Name className="java.lang.String">upos</Name>
  <Value className="java.lang.String">VERB</Value>
</Feature>
<Feature>
  <Name className="java.lang.String">VerbForm</Name>
  <Value className="java.lang.String">Fin</Value>
</Feature>
<Feature>
  <Name className="java.lang.String">category</Name>
  <Value className="java.lang.String">VBP</Value>
</Feature>
</Annotation>
<Annotation Id="13" Type="Token" StartNode="77" EndNode="89">
<Feature>
  <Name className="java.lang.String">head</Name>
  <Value className="java.lang.Integer">31</Value>
</Feature>
<Feature>
  <Name className="java.lang.String">deprel</Name>
  <Value className="java.lang.String">root</Value>
</Feature>
<Feature>
  <Name className="java.lang.String">string</Name>
  <Value className="java.lang.String">confidential</Value>
</Feature>
<Feature>
  <Name className="java.lang.String">Degree</Name>
  <Value className="java.lang.String">Pos</Value>
</Feature>
<Feature>
  <Name className="java.lang.String">lemma</Name>
  <Value className="java.lang.String">confidential</Value>
</Feature>
<Feature>
  <Name className="java.lang.String">upos</Name>
  <Value className="java.lang.String">ADJ</Value>
</Feature>
<Feature>
  <Name className="java.lang.String">category</Name>
  <Value className="java.lang.String">JJ</Value>
</Feature>
</Annotation>
<Annotation Id="14" Type="Token" StartNode="90" EndNode="93">
<Feature>
  <Name className="java.lang.String">head</Name>
  <Value className="java.lang.Integer">15</Value>
</Feature>
<Feature>
  <Name className="java.lang.String">lemma</Name>
  <Value className="java.lang.String">and</Value>
</Feature>
<Feature>
  <Name className="java.lang.String">upos</Name>
  <Value className="java.lang.String">CCONJ</Value>
</Feature>
<Feature>
  <Name className="java.lang.String">deprel</Name>
  <Value className="java.lang.String">cc</Value>
</Feature>
<Feature>
  <Name className="java.lang.String">string</Name>
  <Value className="java.lang.String">and</Value>
</Feature>
<Feature>
  <Name className="java.lang.String">category</Name>
  <Value className="java.lang.String">CC</Value>
</Feature>
</Annotation>
<Annotation Id="15" Type="Token" StartNode="94" EndNode="102">
<Feature>
  <Name className="java.lang.String">Tense</Name>
  <Value className="java.lang.String">Past</Value>
</Feature>
<Feature>
  <Name className="java.lang.String">head</Name>
  <Value className="java.lang.Integer">13</Value>
</Feature>
<Feature>
  <Name className="java.lang.String">deprel</Name>
  <Value className="java.lang.String">conj</Value>
</Feature>
<Feature>
  <Name className="java.lang.String">string</Name>
  <Value className="java.lang.String">intended</Value>
</Feature>
<Feature>
  <Name className="java.lang.String">lemma</Name>
  <Value className="java.lang.String">intend</Value>
</Feature>
<Feature>
  <Name className="java.lang.String">upos</Name>
  <Value className="java.lang.String">VERB</Value>
</Feature>
<Feature>
  <Name className="java.lang.String">VerbForm</Name>
  <Value className="java.lang.String">Part</Value>
</Feature>
<Feature>
  <Name className="java.lang.String">category</Name>
  <Value className="java.lang.String">VBN</Value>
</Feature>
</Annotation>
<Annotation Id="16" Type="Token" StartNode="103" EndNode="109">
<Feature>
  <Name className="java.lang.String">head</Name>
  <Value className="java.lang.Integer">15</Value>
</Feature>
<Feature>
  <Name className="java.lang.String">lemma</Name>
  <Value className="java.lang.String">solely</Value>
</Feature>
<Feature>
  <Name className="java.lang.String">upos</Name>
  <Value className="java.lang.String">ADV</Value>
</Feature>
<Feature>
  <Name className="java.lang.String">deprel</Name>
  <Value className="java.lang.String">advmod</Value>
</Feature>
<Feature>
  <Name className="java.lang.String">string</Name>
  <Value className="java.lang.String">solely</Value>
</Feature>
<Feature>
  <Name className="java.lang.String">category</Name>
  <Value className="java.lang.String">RB</Value>
</Feature>
</Annotation>
<Annotation Id="17" Type="Token" StartNode="110" EndNode="113">
<Feature>
  <Name className="java.lang.String">head</Name>
  <Value className="java.lang.Integer">19</Value>
</Feature>
<Feature>
  <Name className="java.lang.String">lemma</Name>
  <Value className="java.lang.String">for</Value>
</Feature>
<Feature>
  <Name className="java.lang.String">upos</Name>
  <Value className="java.lang.String">ADP</Value>
</Feature>
<Feature>
  <Name className="java.lang.String">deprel</Name>
  <Value className="java.lang.String">case</Value>
</Feature>
<Feature>
  <Name className="java.lang.String">string</Name>
  <Value className="java.lang.String">for</Value>
</Feature>
<Feature>
  <Name className="java.lang.String">category</Name>
  <Value className="java.lang.String">IN</Value>
</Feature>
</Annotation>
<Annotation Id="18" Type="Token" StartNode="114" EndNode="117">
<Feature>
  <Name className="java.lang.String">head</Name>
  <Value className="java.lang.Integer">19</Value>
</Feature>
<Feature>
  <Name className="java.lang.String">deprel</Name>
  <Value className="java.lang.String">det</Value>
</Feature>
<Feature>
  <Name className="java.lang.String">string</Name>
  <Value className="java.lang.String">the</Value>
</Feature>
<Feature>
  <Name className="java.lang.String">lemma</Name>
  <Value className="java.lang.String">the</Value>
</Feature>
<Feature>
  <Name className="java.lang.String">upos</Name>
  <Value className="java.lang.String">DET</Value>
</Feature>
<Feature>
  <Name className="java.lang.String">category</Name>
  <Value className="java.lang.String">DT</Value>
</Feature>
<Feature>
  <Name className="java.lang.String">Definite</Name>
  <Value className="java.lang.String">Def</Value>
</Feature>
<Feature>
  <Name className="java.lang.String">PronType</Name>
  <Value className="java.lang.String">Art</Value>
</Feature>
</Annotation>
<Annotation Id="19" Type="Token" StartNode="118" EndNode="121">
<Feature>
  <Name className="java.lang.String">head</Name>
  <Value className="java.lang.Integer">15</Value>
</Feature>
<Feature>
  <Name className="java.lang.String">deprel</Name>
  <Value className="java.lang.String">obl</Value>
</Feature>
<Feature>
  <Name className="java.lang.String">string</Name>
  <Value className="java.lang.String">use</Value>
</Feature>
<Feature>
  <Name className="java.lang.String">Number</Name>
  <Value className="java.lang.String">Sing</Value>
</Feature>
<Feature>
  <Name className="java.lang.String">lemma</Name>
  <Value className="java.lang.String">use</Value>
</Feature>
<Feature>
  <Name className="java.lang.String">upos</Name>
  <Value className="java.lang.String">NOUN</Value>
</Feature>
<Feature>
  <Name className="java.lang.String">category</Name>
  <Value className="java.lang.String">NN</Value>
</Feature>
</Annotation>
<Annotation Id="20" Type="Token" StartNode="122" EndNode="124">
<Feature>
  <Name className="java.lang.String">head</Name>
  <Value className="java.lang.Integer">22</Value>
</Feature>
<Feature>
  <Name className="java.lang.String">lemma</Name>
  <Value className="java.lang.String">of</Value>
</Feature>
<Feature>
  <Name className="java.lang.String">upos</Name>
  <Value className="java.lang.String">ADP</Value>
</Feature>
<Feature>
  <Name className="java.lang.String">deprel</Name>
  <Value className="java.lang.String">case</Value>
</Feature>
<Feature>
  <Name className="java.lang.String">string</Name>
  <Value className="java.lang.String">of</Value>
</Feature>
<Feature>
  <Name className="java.lang.String">category</Name>
  <Value className="java.lang.String">IN</Value>
</Feature>
</Annotation>
<Annotation Id="21" Type="Token" StartNode="125" EndNode="128">
<Feature>
  <Name className="java.lang.String">head</Name>
  <Value className="java.lang.Integer">22</Value>
</Feature>
<Feature>
  <Name className="java.lang.String">deprel</Name>
  <Value className="java.lang.String">det</Value>
</Feature>
<Feature>
  <Name className="java.lang.String">string</Name>
  <Value className="java.lang.String">the</Value>
</Feature>
<Feature>
  <Name className="java.lang.String">lemma</Name>
  <Value className="java.lang.String">the</Value>
</Feature>
<Feature>
  <Name className="java.lang.String">upos</Name>
  <Value className="java.lang.String">DET</Value>
</Feature>
<Feature>
  <Name className="java.lang.String">category</Name>
  <Value className="java.lang.String">DT</Value>
</Feature>
<Feature>
  <Name className="java.lang.String">Definite</Name>
  <Value className="java.lang.String">Def</Value>
</Feature>
<Feature>
  <Name className="java.lang.String">PronType</Name>
  <Value className="java.lang.String">Art</Value>
</Feature>
</Annotation>
<Annotation Id="22" Type="Token" StartNode="129" EndNode="139">
<Feature>
  <Name className="java.lang.String">head</Name>
  <Value className="java.lang.Integer">19</Value>
</Feature>
<Feature>
  <Name className="java.lang.String">deprel</Name>
  <Value className="java.lang.String">nmod</Value>
</Feature>
<Feature>
  <Name className="java.lang.String">string</Name>
  <Value className="java.lang.String">individual</Value>
</Feature>
<Feature>
  <Name className="java.lang.String">Number</Name>
  <Value className="java.lang.String">Sing</Value>
</Feature>
<Feature>
  <Name className="java.lang.String">lemma</Name>
  <Value className="java.lang.String">individual</Value>
</Feature>
<Feature>
  <Name className="java.lang.String">upos</Name>
  <Value className="java.lang.String">NOUN</Value>
</Feature>
<Feature>
  <Name className="java.lang.String">category</Name>
  <Value className="java.lang.String">NN</Value>
</Feature>
</Annotation>
<Annotation Id="23" Type="Token" StartNode="140" EndNode="142">
<Feature>
  <Name className="java.lang.String">head</Name>
  <Value className="java.lang.Integer">24</Value>
</Feature>
<Feature>
  <Name className="java.lang.String">lemma</Name>
  <Value className="java.lang.String">or</Value>
</Feature>
<Feature>
  <Name className="java.lang.String">upos</Name>
  <Value className="java.lang.String">CCONJ</Value>
</Feature>
<Feature>
  <Name className="java.lang.String">deprel</Name>
  <Value className="java.lang.String">cc</Value>
</Feature>
<Feature>
  <Name className="java.lang.String">string</Name>
  <Value className="java.lang.String">or</Value>
</Feature>
<Feature>
  <Name className="java.lang.String">category</Name>
  <Value className="java.lang.String">CC</Value>
</Feature>
</Annotation>
<Annotation Id="24" Type="Token" StartNode="143" EndNode="149">
<Feature>
  <Name className="java.lang.String">head</Name>
  <Value className="java.lang.Integer">22</Value>
</Feature>
<Feature>
  <Name className="java.lang.String">deprel</Name>
  <Value className="java.lang.String">conj</Value>
</Feature>
<Feature>
  <Name className="java.lang.String">string</Name>
  <Value className="java.lang.String">entity</Value>
</Feature>
<Feature>
  <Name className="java.lang.String">Number</Name>
  <Value className="java.lang.String">Sing</Value>
</Feature>
<Feature>
  <Name className="java.lang.String">lemma</Name>
  <Value className="java.lang.String">entity</Value>
</Feature>
<Feature>
  <Name className="java.lang.String">upos</Name>
  <Value className="java.lang.String">NOUN</Value>
</Feature>
<Feature>
  <Name className="java.lang.String">category</Name>
  <Value className="java.lang.String">NN</Value>
</Feature>
</Annotation>
<Annotation Id="25" Type="Token" StartNode="150" EndNode="152">
<Feature>
  <Name className="java.lang.String">head</Name>
  <Value className="java.lang.Integer">26</Value>
</Feature>
<Feature>
  <Name className="java.lang.String">lemma</Name>
  <Value className="java.lang.String">to</Value>
</Feature>
<Feature>
  <Name className="java.lang.String">upos</Name>
  <Value className="java.lang.String">ADP</Value>
</Feature>
<Feature>
  <Name className="java.lang.String">deprel</Name>
  <Value className="java.lang.String">case</Value>
</Feature>
<Feature>
  <Name className="java.lang.String">string</Name>
  <Value className="java.lang.String">to</Value>
</Feature>
<Feature>
  <Name className="java.lang.String">category</Name>
  <Value className="java.lang.String">IN</Value>
</Feature>
</Annotation>
<Annotation Id="26" Type="Token" StartNode="153" EndNode="157">
<Feature>
  <Name className="java.lang.String">head</Name>
  <Value className="java.lang.Integer">29</Value>
</Feature>
<Feature>
  <Name className="java.lang.String">deprel</Name>
  <Value className="java.lang.String">obl</Value>
</Feature>
<Feature>
  <Name className="java.lang.String">string</Name>
  <Value className="java.lang.String">whom</Value>
</Feature>
<Feature>
  <Name className="java.lang.String">lemma</Name>
  <Value className="java.lang.String">whom</Value>
</Feature>
<Feature>
  <Name className="java.lang.String">upos</Name>
  <Value className="java.lang.String">PRON</Value>
</Feature>
<Feature>
  <Name className="java.lang.String">category</Name>
  <Value className="java.lang.String">WP</Value>
</Feature>
<Feature>
  <Name className="java.lang.String">PronType</Name>
  <Value className="java.lang.String">Rel</Value>
</Feature>
</Annotation>
<Annotation Id="27" Type="Token" StartNode="158" EndNode="162">
<Feature>
  <Name className="java.lang.String">head</Name>
  <Value className="java.lang.Integer">29</Value>
</Feature>
<Feature>
  <Name className="java.lang.String">deprel</Name>
  <Value className="java.lang.String">nsubj:pass</Value>
</Feature>
<Feature>
  <Name className="java.lang.String">string</Name>
  <Value className="java.lang.String">they</Value>
</Feature>
<Feature>
  <Name className="java.lang.String">Number</Name>
  <Value className="java.lang.String">Plur</Value>
</Feature>
<Feature>
  <Name className="java.lang.String">lemma</Name>
  <Value className="java.lang.String">they</Value>
</Feature>
<Feature>
  <Name className="java.lang.String">upos</Name>
  <Value className="java.lang.String">PRON</Value>
</Feature>
<Feature>
  <Name className="java.lang.String">category</Name>
  <Value className="java.lang.String">PRP</Value>
</Feature>
<Feature>
  <Name className="java.lang.String">Person</Name>
  <Value className="java.lang.String">3</Value>
</Feature>
<Feature>
  <Name className="java.lang.String">Case</Name>
  <Value className="java.lang.String">Nom</Value>
</Feature>
<Feature>
  <Name className="java.lang.String">PronType</Name>
  <Value className="java.lang.String">Prs</Value>
</Feature>
</Annotation>
<Annotation Id="28" Type="Token" StartNode="163" EndNode="166">
<Feature>
  <Name className="java.lang.String">Tense</Name>
  <Value className="java.lang.String">Pres</Value>
</Feature>
<Feature>
  <Name className="java.lang.String">head</Name>
  <Value className="java.lang.Integer">29</Value>
</Feature>
<Feature>
  <Name className="java.lang.String">deprel</Name>
  <Value className="java.lang.String">aux:pass</Value>
</Feature>
<Feature>
  <Name className="java.lang.String">Mood</Name>
  <Value className="java.lang.String">Ind</Value>
</Feature>
<Feature>
  <Name className="java.lang.String">string</Name>
  <Value className="java.lang.String">are</Value>
</Feature>
<Feature>
  <Name className="java.lang.String">lemma</Name>
  <Value className="java.lang.String">be</Value>
</Feature>
<Feature>
  <Name className="java.lang.String">upos</Name>
  <Value className="java.lang.String">AUX</Value>
</Feature>
<Feature>
  <Name className="java.lang.String">VerbForm</Name>
  <Value className="java.lang.String">Fin</Value>
</Feature>
<Feature>
  <Name className="java.lang.String">category</Name>
  <Value className="java.lang.String">VBP</Value>
</Feature>
</Annotation>
<Annotation Id="29" Type="Token" StartNode="167" EndNode="176">
<Feature>
  <Name className="java.lang.String">Tense</Name>
  <Value className="java.lang.String">Past</Value>
</Feature>
<Feature>
  <Name className="java.lang.String">head</Name>
  <Value className="java.lang.Integer">22</Value>
</Feature>
<Feature>
  <Name className="java.lang.String">deprel</Name>
  <Value className="java.lang.String">acl:relcl</Value>
</Feature>
<Feature>
  <Name className="java.lang.String">string</Name>
  <Value className="java.lang.String">addressed</Value>
</Feature>
<Feature>
  <Name className="java.lang.String">lemma</Name>
  <Value className="java.lang.String">address</Value>
</Feature>
<Feature>
  <Name className="java.lang.String">upos</Name>
  <Value className="java.lang.String">VERB</Value>
</Feature>
<Feature>
  <Name className="java.lang.String">VerbForm</Name>
  <Value className="java.lang.String">Part</Value>
</Feature>
<Feature>
  <Name className="java.lang.String">category</Name>
  <Value className="java.lang.String">VBN</Value>
</Feature>
<Feature>
  <Name className="java.lang.String">Voice</Name>
  <Value className="java.lang.String">Pass</Value>
</Feature>
</Annotation>
<Annotation Id="30" Type="Token" StartNode="176" EndNode="177">
<Feature>
  <Name className="java.lang.String">head</Name>
  <Value className="java.lang.Integer">13</Value>
</Feature>
<Feature>
  <Name className="java.lang.String">lemma</Name>
  <Value className="java.lang.String">.</Value>
</Feature>
<Feature>
  <Name className="java.lang.String">upos</Name>
  <Value className="java.lang.String">PUNCT</Value>
</Feature>
<Feature>
  <Name className="java.lang.String">deprel</Name>
  <Value className="java.lang.String">punct</Value>
</Feature>
<Feature>
  <Name className="java.lang.String">string</Name>
  <Value className="java.lang.String">.</Value>
</Feature>
<Feature>
  <Name className="java.lang.String">category</Name>
  <Value className="java.lang.String">.</Value>
</Feature>
</Annotation>
<Annotation Id="31" Type="Sentence" StartNode="0" EndNode="177">
<Feature>
  <Name className="java.lang.String">gate.conversion.nLineTo</Name>
  <Value className="java.lang.Integer">50288</Value>
</Feature>
<Feature>
  <Name className="java.lang.String">gate.conversion.nLineFrom</Name>
  <Value className="java.lang.Integer">50257</Value>
</Feature>
<Feature>
  <Name className="java.lang.String">gate.conversion.sentComments</Name>
  <Value className="gate.corpora.ObjectWrapper"><![CDATA[<?xml version='1.1'?><gate.corpora.ObjectWrapper><value class="list"><string># sent_id = email-enronsent12_01-0012</string><string># text = This email and any files transmitted with it from the ElPaso Corporation are confidential and intended solely for the use of the individual or entity to whom they are addressed.</string></value></gate.corpora.ObjectWrapper>]]></Value>
</Feature>
<Feature>
  <Name className="java.lang.String">gate.conversion.nSent</Name>
  <Value className="java.lang.Integer">2301</Value>
</Feature>
<Feature>
  <Name className="java.lang.String">gate.conversion.sentId</Name>
  <Value className="java.lang.String"></Value>
</Feature>
</Annotation>
</AnnotationSet>

</GateDocument>
